svql/__init__.py
svql/ast_visitors/__init__.py
svql/ast_visitors/param_visitor.py
svql/ast_visitors/port_visitor.py
svql/ast_visitors/submodule_inst_visitor.py
svql/core/__init__.py
svql/core/module.py
svql/tables/__init__.py
svql/tables/param.py
svql/tables/port.py
svql/utils/__init__.py
svql/utils/attr_utils.py
svql/utils/string_utils.py
svql-0.1.9.dist-info/LICENSE
svql-0.1.9.dist-info/METADATA
svql-0.1.9.dist-info/WHEEL
svql-0.1.9.dist-info/top_level.txt
svql-0.1.9.dist-info/RECORD
