Metadata-Version: 2.2
Name: svql
Version: 0.1.9
Summary: Query SystemVerilog modules with SQL.
Home-page: https://github.com/etched-ai/svql
Author: sathvik
Author-email: sathvik <sathvik@etched.com>
License: MIT
Classifier: Programming Language :: Python :: 3
Requires-Python: >=3.6
License-File: LICENSE
Requires-Dist: pandas
Requires-Dist: pandasql
Requires-Dist: pyslang
Dynamic: author
Dynamic: home-page
Dynamic: requires-python
